{"ages":"2-5","list_price":49.99,"num_reviews":1.0,"piece_count":67.0,"play_star_rating":5.0,"prod_short_desc":"Get busy with a bulldozer, tipper truck and posable crane!","prod_id":10813.0,"prod_long_desc":"Little construction workers will love these 3 buildable machines. Clear the site with the tracked bulldozer, before tipping new building supplies from the truck. Then use the crane with its claw and posable arm to hoist bricks and construct a building. LEGO\u00ae DUPLO\u00ae bricks are specially designed to be safe for little hands. Includes 3 construction worker DUPLO figures to encourage lots of role-play fun.\nSpark young imaginations with a buildable DUPLO Town construction site full of vehicles and fun!\nToddlers can build and play with the bulldozer, dump truck with tipping bucket, and crane with rotating cabin, movable arm, and working claw \u2013 plus lots of extra bricks\nIncludes three construction worker LEGO DUPLO figures with safety helmets, wheelbarrow, and tools\nLEGO DUPLO building toys are made for small hands and are compatible with other LEGO construction sets for creative building\nBulldozer is over 3\u201d high, 5\u201d long, and 3\u201d wide. Truck is over 4\u201d high, 9\u201d long, and 2\u201d wide. Crane is over 8\u201d high, 11\u201d long, and 4\u201d wide\n67 pieces \u2013 For boys and girls between the ages of 2 and 5 years old","review_difficulty":"Average","set":"Big Construction Site","star_rating":5.0,"theme":"DUPLO\u00ae","val_star_rating":5.0,"country":"US"}