{"ages":"6-12","list_price":9.99,"num_reviews":11.0,"piece_count":91.0,"play_star_rating":4.5,"prod_short_desc":"Speed across distant planets in the micro First Order Snowspeeder\u2122!","prod_id":75126.0,"prod_long_desc":"Engage the enemy with this LEGO\u00ae Microfighters First Order Snowspeeder, featuring a rotating stud shooter with extra ammo and space to sit the included First Order Snowtrooper minifigure with blaster.\nIncludes a First Order Snowtrooper minifigure.\nFeatures big engines, rotating stud shooter and an open cockpit with space for a minifigure to sit.\nFire the rotating stud shooter to repel the enemy\nIncludes a blaster and extra stud shooter ammo.\nAlso includes a First Order Snowtrooper helmet.\nMatch up with the 75125 Resistance X-Wing Fighter microfighter for ice-planet-themed combat.\nMakes a great addition to any microfighter collectible set.\nMeasures over 1\u201d high, 3\u201d long and 2\u201d wide.","review_difficulty":"Easy","set":"First Order Snowspeeder\u2122","star_rating":4.5,"theme":"Star Wars\u2122","val_star_rating":4.5,"country":"US"}