{"ages":"10+","list_price":25.186,"num_reviews":null,"piece_count":209.0,"play_star_rating":null,"prod_short_desc":"Join the Justice League\u2122 with LEGO\u00ae BrickHeadz\u2122 Tactical Batman\u2122 and Superman\u2122!","prod_id":41610.0,"prod_long_desc":"These LEGO\u00ae BrickHeadz\u2122 41610 Tactical Batman\u2122 and Superman\u2122 construction characters are fun to build using colorful LEGO bricks that recreate all their iconic details from the blockbuster Justice League\u2122 movie, including Super Hero costumes and capes. Each stands on a buildable collector's baseplate with BrickHeadz icon for easy display in your home, office or anywhere you like.\nBuildable LEGO\u00ae BrickHeadz\u2122 construction characters featuring Tactical Batman\u2122 and Superman\u2122 have BrickHeadz eyes and authentic details from the blockbuster Justice League\u2122 movie, including iconic Super Hero costumes.\nEach LEGO\u00ae BrickHeadz\u2122 construction character comes with its own buildable collector's baseplate.\nHave fun growing your LEGO\u00ae BrickHeadz\u2122 collection with other classic characters from your favorite movies, TV series, games and comics.\nMash up your LEGO\u00ae BrickHeadz\u2122 construction characters to create super-cool hybrids or your own amazing characters.\nEach character stands over 2\u201d tall without baseplate.\nBaseplates measure over 1\u201d square.","review_difficulty":null,"set":"Tactical Batman\u2122 & Superman\u2122","star_rating":null,"theme":"BrickHeadz","val_star_rating":null,"country":"GB"}