{"ages":"12+","list_price":39.99,"num_reviews":23.0,"piece_count":468.0,"play_star_rating":3.6,"prod_short_desc":"Celebrate London with this LEGO\u00ae Architecture Skyline model!","prod_id":21034.0,"prod_long_desc":"Celebrate the architectural diversity of London with this detailed LEGO\u00ae brick model. The LEGO Architecture Skyline Collection offers models suitable for display in the home and office, and has been developed for all with an interest in travel, architectural culture, history and design. Each set is scaled to give an accurate representation of the comparative size of each structure, with true-to-life color depiction. This set features the National Gallery, Nelson\u2019s Column, London Eye, Big Ben (the Elizabeth Tower) and Tower Bridge, and is finished with a decorative \u201cLondon\u201d nameplate.\nBuild a detailed model of the London skyline!\nModel features the National Gallery, Nelson\u2019s Column, London Eye, Big Ben and Tower Bridge\nIncludes collectible booklet containing information about the design, architecture and history of the building\nLEGO Archiecture models are compatible with all LEGO construction sets for creative building\nMeasures over 5\u201d high, 11\u201d wide and 3\u201d long\n468 pieces \u2013 For boys and girls ages 12 and older","review_difficulty":"Average","set":"London","star_rating":4.7,"theme":"Architecture","val_star_rating":4.1,"country":"US"}