{"ages":"7-14","list_price":17.4724,"num_reviews":11.0,"piece_count":184.0,"play_star_rating":4.8,"prod_short_desc":"Speed into race action with the awesome Scuderia Ferrari SF16-H!","prod_id":75879.0,"prod_long_desc":"Power to victory with this buildable LEGO\u00ae Speed Champions version of the Scuderia Ferrari SF16-H race car, featuring wheels with rubber tires and two interchangeable race numbers so you can pretend to be different Scuderia Ferrari drivers. The set also includes a pit wall with start-finish-line, pit monitor element and checkered flag with waving function, plus wrench and walkie-talkie elements to maximize the role-play fun. Includes a minifigure.\nIncludes a Ferrari racing driver minifigure.\nThe race-ready, buildable Scuderia Ferrari SF16-H features a minifigure cockpit, wheels with rubber tires, two interchangeable race numbers, plus authentic design details and race-graphics stickers.\nSwap the race numbers on the car to play as different Ferrari drivers.\nAlso includes a pit wall featuring a start-finish line with translucent green, orange and red light elements, pit monitor element and checkered flag with waving function.\nAccessory elements include two racing driver helmets, wrench and a walkie-talkie.\nThis set offers an age-appropriate build and play experience for ages 7+.\nScuderia Ferrari SF16-H measures over 1\u201d high, 5\u201d long and 2\u201d wide.\nPit wall measures over 2\u201d high, 3\u201d wide and 3\u201d long.","review_difficulty":"Easy","set":"Scuderia Ferrari SF16-H","star_rating":4.7,"theme":"Speed Champions","val_star_rating":4.7,"country":"AU"}