{"ages":"6-12","list_price":10.1322,"num_reviews":1.0,"piece_count":109.0,"play_star_rating":5.0,"prod_short_desc":"Be an eye in the sky with the 3-in-1 Drone Explorer!","prod_id":31071.0,"prod_long_desc":"Carry out secret missions and explorations with the Drone Explorer, featuring an orange, white and black color scheme, and lots of realistic details, including twin rotors and posable cameras, plus a large opening cockpit and landing gear that doubles as a lifting claw. This 3-in-1 LEGO\u00ae Creator building toy rebuilds into a Swamp Boat or a Propeller Plane for even more action and adventure.\nFuturistic drone featuring lots of cool and realistic details, including twin rotors, posable cameras, large opening cockpit and landing gear that doubles as a lifting claw.\nAlso features an orange, white and black color scheme complete with red navigation lights.\nPrepare for vertical takeoff\u2014then set out on a secret mission.\nGrab objects with the Drone's lifting claw and deliver them to their destination.\nContinue the adventure with this 3-in-1 model. Rebuild the Drone Explorer and take to the marshes aboard a powerful Swamp Boat, or perform daring aerial maneuvers in a classic Propeller Plane.\nThis building toy is suitable for ages 6-12.\nDrone Explorer measures over 2\u201d high, 4\u201d long and 5\u201d wide.\nSwamp Boat measures over 2\u201d high, 4\u201d long and 1\u201d wide.\nPropeller Plane measures over 1\u201d high, 4\u201d long and 4\u201d wide.","review_difficulty":"Average","set":"Drone Explorer","star_rating":5.0,"theme":"LEGO\u00ae Creator 3-in-1","val_star_rating":5.0,"country":"CA"}