{"ages":"9-14","list_price":89.99,"num_reviews":39.0,"piece_count":863.0,"play_star_rating":4.2,"prod_short_desc":"Transport Director Krennic in his armor-plated shuttle!","prod_id":75156.0,"prod_long_desc":"Krennic\u2019s Imperial Shuttle is an intimidating Imperial starship. Featuring huge folding wings and opening front and side panels, this amazing model also has an opening minifigure cockpit, detailed hold with seating for 4 minifigures, a rear ramp with blaster storage, dual spring-loaded shooters and retractable landing skids. Recreate epic space battles from the epic movie, Star Wars: Rogue One, or create your own. Includes 5 minifigures plus a Droid.\nBuild a sinister shuttle with huge folding wings, spring-loaded shooters and more\nFeatured in Rogue One: A Star Wars Story\nIncludes Pao, Director Krennic, Bodhi Rook and 2 Imperial Death Troopers, plus K-2SO droid\nLEGO Star Wars building toys are compatible with all LEGO construction sets for creative building\nMeasures over 17\u201d high, 9\u201d long and 22\u201d wide in flying mode, and over 12\u201d high and 7\u201d wide in landing mode\n863 pieces \u2013 For boys and girls between the ages of 9 and 14 years old","review_difficulty":"Average","set":"Krennic's Imperial Shuttle","star_rating":4.4,"theme":"Star Wars\u2122","val_star_rating":4.4,"country":"US"}