{"ages":"9-16","list_price":49.99,"num_reviews":9.0,"piece_count":476.0,"play_star_rating":4.1,"prod_short_desc":"Call in the powerful Mine Loader!","prod_id":42049.0,"prod_long_desc":"Head underground aboard this authentic replica of a real-life mine loader, featuring a yellow and black color scheme, versatile working grabber, detailed engine with moving pistons, articulated central steering mechanism and huge tires. This rugged 2-in-1 LEGO\u00ae Technic model also includes a cargo element, and can be rebuilt to create a Mine Cutting Machine for a double build-and-play experience! Digital 3D building instructions for both models are available online.\nBuild a lifelike Mine Loader with a working grabber, articulated steering and moving pistons!\nvehicles in 1 \u2013 Rebuilds into a Mine Cutting Machine\nIncludes detailed engine and driver\u2019s cab with orange warning beacon\nLEGO Technic building toys are compatible with all LEGO construction sets for creative building\nMine Loader measures 13\u201d long, 7\u201d wide, and 2\u201d high\n476 pieces \u2013 For boys and girls between the ages of 9 and 16 years old\nInteractive 3D Digital LEGO Building Instructions app available online for both A and B models","review_difficulty":"Average","set":"Mine Loader","star_rating":4.3,"theme":"Technic","val_star_rating":4.1,"country":"US"}