{"ages":"5-12","list_price":24.3878,"num_reviews":6.0,"piece_count":190.0,"play_star_rating":4.2,"prod_short_desc":"Transport the mountain snowboarder to the hospital!","prod_id":60179.0,"prod_long_desc":"Join the LEGO\u00ae City rescue team and fly the Ambulance Helicopter! This fun toy features spinning rotors, hatch on the back, landing gear and room for a stretcher inside, plus snowboard and radio elements, and 3 minifigures.\nIncludes 3 minifigures: a pilot, doctor and a snowboarder.\nFeatures a red and yellow Ambulance Helicopter with spinning rotors, landing gear, hatch on the back and room for a stretcher inside.\nSpin the rotor to launch the helicopter.\nOpen the hatch to fit the stretcher inside the back.\nAccessory elements include a snowboard, stretcher and a radio.\nThis fun toy is suitable for ages 5-12.\nHelicopter measures over 3\u201d high, 11\u201d long and 3\u201d wide.\nAs seen in the LEGO\u00ae City Vehicles TV commercial.","review_difficulty":"Easy","set":"Ambulance Helicopter","star_rating":3.8,"theme":"City","val_star_rating":4.7,"country":"IT"}